snowflake/snowpark_connect/__init__.py
snowflake/snowpark_connect/column_name_handler.py
snowflake/snowpark_connect/column_qualifier.py
snowflake/snowpark_connect/config.py
snowflake/snowpark_connect/constants.py
snowflake/snowpark_connect/control_server.py
snowflake/snowpark_connect/dataframe_container.py
snowflake/snowpark_connect/dataframe_name_handler.py
snowflake/snowpark_connect/date_time_format_mapping.py
snowflake/snowpark_connect/resources_initializer.py
snowflake/snowpark_connect/server.py
snowflake/snowpark_connect/snowflake_session.py
snowflake/snowpark_connect/start_server.py
snowflake/snowpark_connect/tcm.py
snowflake/snowpark_connect/type_mapping.py
snowflake/snowpark_connect/type_support.py
snowflake/snowpark_connect/typed_column.py
snowflake/snowpark_connect/version.py
snowflake/snowpark_connect/analyze_plan/__init__.py
snowflake/snowpark_connect/analyze_plan/map_tree_string.py
snowflake/snowpark_connect/client/__init__.py
snowflake/snowpark_connect/client/error_utils.py
snowflake/snowpark_connect/client/exceptions.py
snowflake/snowpark_connect/client/query_results.py
snowflake/snowpark_connect/client/server.py
snowflake/snowpark_connect/client/utils/__init__.py
snowflake/snowpark_connect/client/utils/session.py
snowflake/snowpark_connect/error/__init__.py
snowflake/snowpark_connect/error/error_codes.py
snowflake/snowpark_connect/error/error_mapping.py
snowflake/snowpark_connect/error/error_utils.py
snowflake/snowpark_connect/error/exceptions.py
snowflake/snowpark_connect/execute_plan/__init__.py
snowflake/snowpark_connect/execute_plan/map_execution_command.py
snowflake/snowpark_connect/execute_plan/map_execution_root.py
snowflake/snowpark_connect/execute_plan/utils.py
snowflake/snowpark_connect/expression/__init__.py
snowflake/snowpark_connect/expression/error_utils.py
snowflake/snowpark_connect/expression/function_defaults.py
snowflake/snowpark_connect/expression/hybrid_column_map.py
snowflake/snowpark_connect/expression/integral_types_support.py
snowpark_connect-1.9.0.dist-info/licenses/LICENSE-binary
snowpark_connect-1.9.0.dist-info/licenses/LICENSE.txt
snowpark_connect-1.9.0.dist-info/licenses/NOTICE-binary
snowpark_connect-1.9.0.dist-info/METADATA
snowpark_connect-1.9.0.dist-info/WHEEL
snowpark_connect-1.9.0.dist-info/top_level.txt
snowpark_connect-1.9.0.dist-info/RECORD
